jumpstarter_cli_admin/__init__.py
jumpstarter_cli_admin/__main__.py
jumpstarter_cli_admin/controller.py
jumpstarter_cli_admin/create.py
jumpstarter_cli_admin/create_test.py
jumpstarter_cli_admin/delete.py
jumpstarter_cli_admin/delete_test.py
jumpstarter_cli_admin/get.py
jumpstarter_cli_admin/get_test.py
jumpstarter_cli_admin/import_res.py
jumpstarter_cli_admin/import_res_test.py
jumpstarter_cli_admin/install.py
jumpstarter_cli_admin/install_test.py
jumpstarter_cli_admin/k8s.py
jumpstarter_cli_admin/py.typed
jumpstarter_cli_admin/test_utils.py
jumpstarter_cli_admin-0.7.4.dist-info/METADATA
jumpstarter_cli_admin-0.7.4.dist-info/WHEEL
jumpstarter_cli_admin-0.7.4.dist-info/entry_points.txt
jumpstarter_cli_admin-0.7.4.dist-info/RECORD
