Metadata-Version: 2.4
Name: jumpstarter-cli-admin
Version: 0.7.4
Project-URL: Homepage, https://jumpstarter.dev
Project-URL: source_archive, https://github.com/jumpstarter-dev/repo/archive/c5d38de69eadbb8eb0388bcfe3430a679fff0059.zip
Author-email: Kirk Brauer <kbrauer@hatci.com>
License-Expression: Apache-2.0
Requires-Python: >=3.11
Requires-Dist: aiohttp>=3.11.18
Requires-Dist: jumpstarter-cli-common==0.7.4
Requires-Dist: jumpstarter-kubernetes==0.7.4
Requires-Dist: packaging>=25.0
Requires-Dist: semver~=2.13
